<?xml version="1.0" encoding="utf-8" ?>
<sqlMap namespace="EntityModel" xmlns="http://ibatis.apache.org/mapping"
		xmlns:xsi="http://www.w3.org/2001/XMLSchema-instance">

	<alias>
		<!--类的别名-->
		<typeAlias alias="Product" type="Web.Product,Web"/>
	</alias>

	<resultMaps>
		<!--Product类与db表的映射-->
		<resultMap id="SelectAllResult" class="Product">
			<result property="ProductId" column="product_id"/>
			<result property="ProductName" column="product_name"/>
			<result property="ProductCompany" column="product_company" />
			<result property="SignDate" column="sign_date"  />
			<result property="UpdateDate" column="update_date" />
		</resultMap>
	</resultMaps>

	<statements>

		<!--查询所有记录-->
		<select id="SelectAllProduct" resultMap="SelectAllResult">
			<![CDATA[SELECT Product_Id,Product_Name,Product_Company,Sign_Date,Update_Date FROM Product]]>
		</select>

		<!--查询单条记录-->
		<select id="SelectByProductId" parameterClass="int" resultMap="SelectAllResult" extends="SelectAllProduct">
			<![CDATA[ where Product_Id = #value#  ]]>
		</select>

		<!--插入新记录-->
		<insert id="InsertProduct" parameterClass="Product" >
			<!--oracle sequence的示例用法-->
			<selectKey property="ProductId" type="pre" resultClass="int">
				SELECT nextval('product_product_id_seq')
			</selectKey>
			<![CDATA[INSERT into product(product_id, product_company, product_name, sign_date, update_date)
			VALUES(#ProductId#,#ProductCompany#, #ProductName# , #SignDate# , #UpdateDate#)]]>
		</insert>

		<!--更新单条记录-->
		<update id="UpdateProduct" parameterClass="Product">
			<![CDATA[Update Product SET ProductName=#ProductName#,
			ProductCompany=#ProductCompany#,			
			SignDate=#SignDate#,
			UpdateDate=#UpdateDate#
			Where ProductId=#ProductId#]]>
		</update>

		<!--根据主键删除单条记录-->
		<delete id="DeleteProductById" parameterClass="int">
			<![CDATA[Delete From Product Where ProductId=#value#]]>
		</delete>


	</statements>

</sqlMap>

